MANIFEST.in
README
distribute_setup.py
setup.py
src/django_qmixin.egg-info/PKG-INFO
src/django_qmixin.egg-info/SOURCES.txt
src/django_qmixin.egg-info/dependency_links.txt
src/django_qmixin.egg-info/top_level.txt
src/djqmixin/__init__.py