Metadata-Version: 1.0
Name: django-qmixin
Version: 0.1
Summary: A Django app for extending managers and the querysets they produce.
Home-page: http://bitbucket.org/zacharyvoase/django-qmixin
Author: Zachary Voase
Author-email: zacharyvoase@me.com
License: UNKNOWN
Platform: UNKNOWN
